ironicclient/__init__.py
ironicclient/client.py
ironicclient/exc.py
ironicclient/shell.py
ironicclient/common/__init__.py
ironicclient/common/base.py
ironicclient/common/filecache.py
ironicclient/common/http.py
ironicclient/common/i18n.py
ironicclient/common/utils.py
ironicclient/common/apiclient/__init__.py
ironicclient/common/apiclient/base.py
ironicclient/common/apiclient/exceptions.py
ironicclient/osc/__init__.py
ironicclient/osc/plugin.py
ironicclient/osc/v1/__init__.py
ironicclient/osc/v1/baremetal_allocation.py
ironicclient/osc/v1/baremetal_chassis.py
ironicclient/osc/v1/baremetal_conductor.py
ironicclient/osc/v1/baremetal_create.py
ironicclient/osc/v1/baremetal_deploy_template.py
ironicclient/osc/v1/baremetal_driver.py
ironicclient/osc/v1/baremetal_inspection_rule.py
ironicclient/osc/v1/baremetal_node.py
ironicclient/osc/v1/baremetal_port.py
ironicclient/osc/v1/baremetal_portgroup.py
ironicclient/osc/v1/baremetal_runbook.py
ironicclient/osc/v1/baremetal_shard.py
ironicclient/osc/v1/baremetal_volume_connector.py
ironicclient/osc/v1/baremetal_volume_target.py
ironicclient/tests/__init__.py
ironicclient/tests/functional/osc/v1/test_baremetal_chassis_create.py
ironicclient/tests/unit/__init__.py
ironicclient/tests/unit/test_client.py
ironicclient/tests/unit/test_exc.py
ironicclient/tests/unit/test_import.py
ironicclient/tests/unit/utils.py
ironicclient/tests/unit/common/__init__.py
ironicclient/tests/unit/common/test_base.py
ironicclient/tests/unit/common/test_filecache.py
ironicclient/tests/unit/common/test_http.py
ironicclient/tests/unit/common/test_utils.py
ironicclient/tests/unit/common/apiclient/__init__.py
ironicclient/tests/unit/common/apiclient/test_base.py
ironicclient/tests/unit/common/apiclient/test_exceptions.py
ironicclient/tests/unit/osc/__init__.py
ironicclient/tests/unit/osc/fakes.py
ironicclient/tests/unit/osc/test_plugin.py
ironicclient/tests/unit/osc/v1/__init__.py
ironicclient/tests/unit/osc/v1/fakes.py
python_ironicclient-5.15.0.dist-info/licenses/AUTHORS
python_ironicclient-5.15.0.dist-info/licenses/LICENSE
python_ironicclient-5.15.0.dist-info/METADATA
python_ironicclient-5.15.0.dist-info/WHEEL
python_ironicclient-5.15.0.dist-info/entry_points.txt
python_ironicclient-5.15.0.dist-info/pbr.json
python_ironicclient-5.15.0.dist-info/top_level.txt
python_ironicclient-5.15.0.dist-info/RECORD
