Metadata-Version: 2.4
Name: python-ironicclient
Version: 5.15.0
Summary: OpenStack Bare Metal Provisioning API Client Library
Home-page: https://docs.openstack.org/python-ironicclient/latest/
Author: OpenStack
Author-email: openstack-discuss@lists.openstack.org
Classifier: Environment :: OpenStack
Classifier: Intended Audience :: Information Technology
Classifier: Intended Audience :: System Administrators
Classifier: License :: OSI Approved :: Apache Software License
Classifier: Operating System :: POSIX :: Linux
Classifier: Programming Language :: Python
Classifier: Programming Language :: Python :: Implementation :: CPython
Classifier: Programming Language :: Python :: 3 :: Only
Classifier: Programming Language :: Python :: 3
Classifier: Programming Language :: Python :: 3.10
Classifier: Programming Language :: Python :: 3.11
Classifier: Programming Language :: Python :: 3.12
Requires-Python: >=3.10
License-File: LICENSE
License-File: AUTHORS
Requires-Dist: pbr>=6.0.0
Requires-Dist: platformdirs>=3
Requires-Dist: cliff>=2.8.0
Requires-Dist: dogpile.cache>=0.8.0
Requires-Dist: jsonschema>=3.2.0
Requires-Dist: keystoneauth1>=3.11.0
Requires-Dist: openstacksdk>=0.18.0
Requires-Dist: osc-lib>=2.0.0
Requires-Dist: oslo.utils>=3.33.0
Requires-Dist: PyYAML>=3.13
Requires-Dist: requests>=2.14.2
Requires-Dist: stevedore>=1.20.0
Provides-Extra: cli
Requires-Dist: python-openstackclient>=3.12.0; extra == "cli"
Provides-Extra: test
Requires-Dist: coverage>=4.0; extra == "test"
Requires-Dist: fixtures>=3.0.0; extra == "test"
Requires-Dist: requests-mock>=1.2.0; extra == "test"
Requires-Dist: oslotest>=3.2.0; extra == "test"
Requires-Dist: testtools>=2.2.0; extra == "test"
Requires-Dist: tempest>=17.1.0; extra == "test"
Requires-Dist: stestr>=1.0.0; extra == "test"
Requires-Dist: ddt>=1.0.1; extra == "test"
Requires-Dist: python-openstackclient>=3.12.0; extra == "test"
Dynamic: author
Dynamic: author-email
Dynamic: classifier
Dynamic: description
Dynamic: home-page
Dynamic: license-file
Dynamic: provides-extra
Dynamic: requires-dist
Dynamic: requires-python
Dynamic: summary
